collective.ttwpo-1.0b5-py2.7-nspkg.pth
collective/ttwpo/__init__.py
collective/ttwpo/api.py
collective/ttwpo/configure.zcml
collective/ttwpo/gettextmessagecatalog.py
collective/ttwpo/interfaces.py
collective/ttwpo/register.py
collective/ttwpo/resources.py
collective/ttwpo/setuphandlers.py
collective/ttwpo/storage.py
collective/ttwpo/testing.py
collective/ttwpo/translationdomain.py
collective/ttwpo/browser/__init__.py
collective/ttwpo/browser/configure.zcml
collective/ttwpo/browser/controlpanel.pt
collective/ttwpo/browser/controlpanel.py
collective/ttwpo/browser/manage.pt
collective/ttwpo/browser/manage.py
collective/ttwpo/browser/static/.gitkeep
collective/ttwpo/locales/collective.zanata.pot
collective/ttwpo/locales/update.sh
collective/ttwpo/profiles/default/browserlayer.xml
collective/ttwpo/profiles/default/controlpanel.xml
collective/ttwpo/profiles/default/metadata.xml
collective/ttwpo/profiles/uninstall/browserlayer.xml
collective/ttwpo/profiles/uninstall/controlpanel.xml
collective/ttwpo/syncer/__init__.py
collective/ttwpo/syncer/configure.zcml
collective/ttwpo/syncer/zanata.py
collective/ttwpo/tests/__init__.py
collective/ttwpo/tests/data.py
collective/ttwpo/tests/test_api.py
collective/ttwpo/tests/test_gettextmsgcat.py
collective/ttwpo/tests/test_register.py
collective/ttwpo/tests/test_setup.py
collective/ttwpo/tests/test_storage.py
collective/ttwpo/tests/test_translationdomain.py
collective.ttwpo-1.0b5.dist-info/DESCRIPTION.rst
collective.ttwpo-1.0b5.dist-info/METADATA
collective.ttwpo-1.0b5.dist-info/RECORD
collective.ttwpo-1.0b5.dist-info/WHEEL
collective.ttwpo-1.0b5.dist-info/entry_points.txt
collective.ttwpo-1.0b5.dist-info/metadata.json
collective.ttwpo-1.0b5.dist-info/namespace_packages.txt
collective.ttwpo-1.0b5.dist-info/top_level.txt
